tkvdb/__init__.py
tkvdb/ctkvdb.pxd
tkvdb/cursor.cpython-313-x86_64-linux-gnu.so
tkvdb/cursor.pxd
tkvdb/db.cpython-313-x86_64-linux-gnu.so
tkvdb/db.pxd
tkvdb/errors.cpython-313-x86_64-linux-gnu.so
tkvdb/errors.pxd
tkvdb/iterators.cpython-313-x86_64-linux-gnu.so
tkvdb/iterators.pxd
tkvdb/params.cpython-313-x86_64-linux-gnu.so
tkvdb/params.pxd
tkvdb/transaction.cpython-313-x86_64-linux-gnu.so
tkvdb/transaction.pxd
python_tkvdb-0.2.3.dist-info/LICENSE
python_tkvdb-0.2.3.dist-info/METADATA
python_tkvdb-0.2.3.dist-info/WHEEL
python_tkvdb-0.2.3.dist-info/top_level.txt
python_tkvdb-0.2.3.dist-info/RECORD
